comma_fixer/__init.py__
comma_fixer/column.py
comma_fixer/fixer.py
comma_fixer/parsed.py
comma_fixer/schema.py
comma_fixer-1.0.8.dist-info/METADATA
comma_fixer-1.0.8.dist-info/WHEEL
comma_fixer-1.0.8.dist-info/licenses/LICENSE.txt
comma_fixer-1.0.8.dist-info/RECORD
