Metadata-Version: 2.4
Name: comma-fixer
Version: 1.0.8
Summary: 
License-File: LICENSE.txt
Author: The Gang Technology
Requires-Python: >=3.12
Classifier: Programming Language :: Python :: 3
Classifier: Programming Language :: Python :: 3.12
Classifier: Programming Language :: Python :: 3.13
Classifier: Programming Language :: Python :: 3.14
Requires-Dist: build (>=1.3.0,<2.0.0)
Requires-Dist: jinja2 (>=3.1.6,<4.0.0)
Requires-Dist: networkx (>=3.5,<4.0)
Requires-Dist: numpy (>=2.3.2,<3.0.0)
Requires-Dist: pandas (>=2.3.2,<3.0.0)
Project-URL: Homepage, https://github.com/thegangtechnology/comma-fixer
Project-URL: Issues, https://github.com/thegangtechnology/comma-fixer/issues
